mpesasync/__init__.py
mpesasync/certificates/ProductionCertificate.cer
mpesasync/certificates/SandboxCertificate.cer
mpesasync/contracts/__init__.py
mpesasync/lipa_na_mpesa.py
mpesasync/mpesa_business/__init__.py
mpesasync/mpesa_business/mpesa_business.py
mpesasync/mpesa_business/transactions.py
mpesasync/restlib.py
mpesasync/types.py
mpesasync-1.0.0.dist-info/WHEEL
mpesasync-1.0.0.dist-info/METADATA
mpesasync-1.0.0.dist-info/RECORD
