Metadata-Version: 2.1
Name: mpesasync
Version: 1.0.0
Summary: A Mpesa Daraja API library to quickly get started sending and receiving money from mpesa 
Home-page: https://github.com/Piusdan/mpesasync
License: MIT
Author: Pius Dan
Author-email: npiusdan@gmail.com
Maintainer: Pius Dan(darklotus)
Maintainer-email: npiusdan@gmail.com
Requires-Python: >=3.9,<4.0
Classifier: License :: OSI Approved :: MIT License
Classifier: Operating System :: OS Independent
Classifier: Programming Language :: Python :: 3
Classifier: Programming Language :: Python :: 3.10
Classifier: Programming Language :: Python :: 3.9
Requires-Dist: aiohttp (>=3.8.1,<4.0.0)
Requires-Dist: cryptography (>=36.0.1,<37.0.0)
Requires-Dist: httpx (>=0.19.0,<0.20.0)
Requires-Dist: pydantic (>=1.8.2,<2.0.0)
Requires-Dist: ujson (>=5.1.0,<6.0.0)
Project-URL: Bug Tracker, https://github.com/Piusdan/mpesasync/issues
Project-URL: Repository, https://github.com/Piusdan/mpesasync
